stargql/__init__.py
stargql/__version__.py
stargql/applications.py
stargql/subscription.py
starlette_graphql_zifulu-0.0.3.dist-info/LICENSE
starlette_graphql_zifulu-0.0.3.dist-info/METADATA
starlette_graphql_zifulu-0.0.3.dist-info/WHEEL
starlette_graphql_zifulu-0.0.3.dist-info/top_level.txt
starlette_graphql_zifulu-0.0.3.dist-info/RECORD
