Metadata-Version: 2.1
Name: starlette-graphql-zifulu
Version: 0.0.3
Summary: GraphQL Server via Starlette
Home-page: https://github.com/pypa/sampleproject
Author: zifulu
Author-email: zifulu@zifulu.com
License: UNKNOWN
Platform: UNKNOWN
Classifier: Programming Language :: Python :: 3
Classifier: License :: OSI Approved :: MIT License
Classifier: Operating System :: OS Independent
Requires-Python: >=3.7
License-File: LICENSE
Requires-Dist: graphql-core (==3.1.0)
Requires-Dist: python-gql (==0.1.2)
Requires-Dist: starlette (==0.17.1)
Requires-Dist: typing-extensions (==3.7.4.2)
Requires-Dist: gql-subscriptions (==0.0.2)
